orbis_plugin_aggregation_gold_gs/__init__.py
orbis_plugin_aggregation_gold_gs/main.py
orbis_plugin_aggregation_gold_gs-2.2.4.dist-info/LICENSE
orbis_plugin_aggregation_gold_gs-2.2.4.dist-info/METADATA
orbis_plugin_aggregation_gold_gs-2.2.4.dist-info/WHEEL
orbis_plugin_aggregation_gold_gs-2.2.4.dist-info/top_level.txt
orbis_plugin_aggregation_gold_gs-2.2.4.dist-info/RECORD
