Metadata-Version: 2.1
Name: orbis-plugin-aggregation-gold-gs
Version: 2.2.4
Summary: The gold_gs aggregation plugin for Orbis
Home-page: https://github.com/orbis-eval/orbis_plugin_aggregation_gold_gs
Author: fabod
License: GPL2
Platform: UNKNOWN
Requires-Python: >3.6
